{
	"info": {
		"url_png_icon_64x64": "https://oznode.xevrac.com/img/oznode_logo.png",
		"url_png_logo": "https://oznode.xevrac.com/img/oznode_logo.png",
		"location": "New South Wales, Australia",
		"social": {
			"twitter_handle": "OzNode_",
			"telegram_handle": "xevrac",
			"facebook_handle": "",
			"youtube_handle": "",
			"twitch_handle": "",
			"discord_handle": "",
			"github_handle": ""
		},
		"company": {
			"name": "OzNode",
			"addr": "",
			"city": "",
			"country": "Australia",
			"company_id": "",
			"vat_id": ""
		},
		"about": {
			"me": "This is OzNode. A bleeding edge blockchain technology based community awareness project, hosted in AU.",
			"server": "Our network infrastructure has been fully developed in-house. From the robust bare-metal servers we administrate, to our website. It's been built from the ground up; no middle man whatsoever.",
			"company": ""
		},
		"my-pool-ids": {
			"0": "2bd08fe7aa13127662f5aca7b0d85f9104cb4787aa03d957f5205d85"
		},
		"telegram-admin-handle": {
			"0": "xevrac"
		},
		"adapools_ext": {
			"prometheus": {
				"0": {
					"name": "OzNode Relay",
					"type": "relay",
					"key": "oznode.ddns.net:3001"
				},
				"1": {
					"name": "OzNode Relay - Partner",
					"type": "relay",
					"key": "aps2-1.adrawnarrow.io:6000"
				},
				"2": {
					"name": "OzNode",
					"type": "bp",
					"key": "oznode.ddns.net:6000"
				}
			}
		}
	}
}