{
	"info": {
		"url_png_icon_64x64": "https://www.helenspool.eu/icons/helen64x64.png",
		"url_png_logo": "https://www.helenspool.eu/helenslogo.png",
		"location": "Fráncfort, Europe",
		"social": {
			"twitter_handle": "HelenStakePool",
			"telegram_handle": "@HelenSPool",
			"reddit_handle": "u/HelenStakePoolBot"
		},
		"about": {
			"me": "Contact with @HelenspoolBot. It's a bot but it can help you communicate with me in 12 languages (use /call).",
			"server": "As much as Cardano network needs"
		}
	},
	"my-pool-ids": [
		"771d339ddd290d6d4888eae41dc3e26ff2bb13143c4ff8d7b6c68848"
	],
	"when-satured-then-recommend": [],
	"telegram-admin-handle": [
		"@HelenspoolBot"
	],
	"itn": {
		"owner": "",
		"witness": ""
	}
}